HW3/HW3.v

module Memory(clock, instruction, data, address);
    inout [15:0] data;
    input [11:0] address;
    input clock;
    input instruction;

    reg [15:0] memory[2**12 - 1 : 0];
    reg [15:0] data_in;

    assign data = instruction ? data_in : 'hz;

    always @(posedge clock)
    begin
   	if(instruction)
    	data_in = memory[address];
   	else
    	memory[address] = data;
    end
endmodule

module TestBench;
    reg [15:0] data_in;
    reg [11:0] address;
    reg clock;
    reg instruction;
    wire [15:0] data;

    Memory mem(clock, instruction, data, address);

    assign data = instruction ? 'hz : data_in;

    initial begin
        clock = 0;
    end

    always
    #5 clock = ~clock;
    initial begin
	$dumpfile("HW3_99101087.vcd"); $dumpvars;
	address = 12'h1a1;
        instruction = 1;
        #11
	address = 12'h123;
        instruction = 1;
        #11
	instruction = 0;
	#11
        address = 12'h1a1;
        data_in = 16'd81;
        #11
	address = 12'h123;
        data_in = 16'd43;
        #11
	instruction = 1;
	#11
        address = 12'h1a1;
        #11
	address = 12'h123;
        #11
	instruction = 0;
	#13
	address = 12'h1a1;
        data_in = 16'd24;
        #11
	address = 12'h123;
        data_in = 16'd74;
        #11
	instruction = 1;
	#11
	address = 12'h1a1;
        #13
	address = 12'h123;
        #11
	instruction = 0;
	#11
	address = 12'h1a1;
        data_in = 16'd35;
        #23
	address = 12'h1a1;
        instruction = 1;
        #23
	$finish;
    end
endmodule

HW3/HW3_99101087.vcd
$date
	Sat Jun 03 14:20:32 2023
$end
$version
	ModelSim Version 2020.4
$end
$timescale
	1ns
$end

$scope module TestBench $end
$var reg 16 ! data_in [15:0] $end
$var reg 12 " address [11:0] $end
$var reg 1 # clock $end
$var reg 1 $ instruction $end
$var wire 1 % data [15] $end
$var wire 1 & data [14] $end
$var wire 1 ' data [13] $end
$var wire 1 ( data [12] $end
$var wire 1 ) data [11] $end
$var wire 1 * data [10] $end
$var wire 1 + data [9] $end
$var wire 1 , data [8] $end
$var wire 1 - data [7] $end
$var wire 1 . data [6] $end
$var wire 1 / data [5] $end
$var wire 1 0 data [4] $end
$var wire 1 1 data [3] $end
$var wire 1 2 data [2] $end
$var wire 1 3 data [1] $end
$var wire 1 4 data [0] $end

$scope module mem $end
$var wire 1 % data [15] $end
$var wire 1 & data [14] $end
$var wire 1 ' data [13] $end
$var wire 1 ( data [12] $end
$var wire 1 ) data [11] $end
$var wire 1 * data [10] $end
$var wire 1 + data [9] $end
$var wire 1 , data [8] $end
$var wire 1 - data [7] $end
$var wire 1 . data [6] $end
$var wire 1 / data [5] $end
$var wire 1 0 data [4] $end
$var wire 1 1 data [3] $end
$var wire 1 2 data [2] $end
$var wire 1 3 data [1] $end
$var wire 1 4 data [0] $end
$var wire 1 5 address [11] $end
$var wire 1 6 address [10] $end
$var wire 1 7 address [9] $end
$var wire 1 8 address [8] $end
$var wire 1 9 address [7] $end
$var wire 1 : address [6] $end
$var wire 1 ; address [5] $end
$var wire 1 < address [4] $end
$var wire 1 = address [3] $end
$var wire 1 > address [2] $end
$var wire 1 ? address [1] $end
$var wire 1 @ address [0] $end
$var wire 1 A clock $end
$var wire 1 B instruction $end
$var reg 16 C data_in [15:0] $end
$upscope $end
$upscope $end
$enddefinitions $end
#0
$dumpvars
bx !
b110100001 "
0#
1$
bx C
x4
x3
x2
x1
x0
x/
x.
x-
x,
x+
x*
x)
x(
x'
x&
x%
1@
0?
0>
0=
0<
1;
0:
19
18
07
06
05
1B
0A
$end
#5
1#
1A
#10
0#
0A
#11
b100100011 "
1?
09
#15
1#
1A
#20
0#
0A
#22
0$
0B
#25
1#
1A
#30
0#
0A
#33
b110100001 "
b1010001 !
14
03
02
01
10
0/
1.
0-
0,
0+
0*
0)
0(
0'
0&
0%
0?
19
#35
1#
1A
#40
0#
0A
#44
b100100011 "
b101011 !
13
11
00
1/
0.
1?
09
#45
1#
1A
#50
0#
0A
#55
1$
1#
z4
z3
z2
z1
z0
z/
z.
z-
z,
z+
z*
z)
z(
z'
z&
z%
1B
x4
x3
x2
x1
x0
x/
x.
x-
x,
x+
x*
x)
x(
x'
x&
x%
1A
b101011 C
14
13
02
11
00
1/
0.
0-
0,
0+
0*
0)
0(
0'
0&
0%
#60
0#
0A
#65
1#
1A
#66
b110100001 "
0?
19
#70
0#
0A
#75
1#
1A
b1010001 C
03
01
10
0/
1.
#77
b100100011 "
1?
09
#80
0#
0A
#85
1#
1A
b101011 C
13
11
00
1/
0.
#88
0$
0B
#90
0#
0A
#95
1#
1A
#100
0#
0A
#101
b110100001 "
b11000 !
04
03
10
0/
0?
19
#105
1#
1A
#110
0#
0A
#112
b100100011 "
b1001010 !
13
00
1.
1?
09
#115
1#
1A
#120
0#
0A
#123
1$
z4
z3
z2
z1
z0
z/
z.
z-
z,
z+
z*
z)
z(
z'
z&
z%
1B
14
13
02
11
00
1/
0.
0-
0,
0+
0*
0)
0(
0'
0&
0%
#125
1#
1A
b1001010 C
04
0/
1.
#130
0#
0A
#134
b110100001 "
0?
19
#135
1#
1A
b11000 C
03
10
0.
#140
0#
0A
#145
1#
1A
#147
b100100011 "
1?
09
#150
0#
0A
#155
1#
1A
b1001010 C
13
00
1.
#158
0$
0B
#160
0#
0A
#165
1#
1A
#169
b110100001 "
b100011 !
14
01
1/
0.
0?
19
#170
0#
0A
#175
1#
1A
#180
0#
0A
#185
1#
1A
#190
0#
0A
#192
1$
z4
z3
z2
z1
z0
z/
z.
z-
z,
z+
z*
z)
z(
z'
z&
z%
1B
04
13
02
11
00
0/
1.
0-
0,
0+
0*
0)
0(
0'
0&
0%
#195
1#
1A
b100011 C
14
01
1/
0.
